Workbook

Sheet Punkte-Definition
A1: Definition der Punktevergabe für das Punktesystem
B3: Realwert (CHF) | C3: Punkte | D3: Punkte-pro-CHF | E3: CHF-pro-Punkt (Belohnungswert ohne Ziel-Kostenanteil) | F3: Belohnungswert mit 50% Vereins-Kostenanteil
A4: Umrechnungskurs | B4: 1 | C4: 15 | D4: =C4/B4 -> 15 | E4: =C4/D4 -> 1 | F4: =E4*0.5 -> 0.5
B6: Spendenwert (CHF) | C6: Punkte | D6: Punkte-pro-CHF | E6: CHF-pro-Spendenpunkt (Belohnungswert ohne Ziel-Kostenanteil) | F6: CHF mit 50% Vereins-Kostenanteil
A7: Spende | B7: 1 | C7: 5 | D7: =C7/B7 -> 5 | E7: =D7/D4 -> 0.33333333 | F7: =E7*0.5 -> 0.16666667
A9: Aufwandsentschädigung | B9: Arbeits-Stunden (h) | C9: Punkte | D9: Punkte-pro-h | E9: CHF-pro-Aufwands-Stunde (Belohnungswert ohne Ziel-Kostenanteil) | F9: CHF mit 50% Vereins-Kostenanteil
A10: Aufgaben (z. B. Social Media, Events) | B10: 1 | C10: 30 | D10: =C10/B10 -> 30 | E10: =D10/D4 -> 2 | F10: =E10*0.5 -> 1
A12: Aufwandsentschädigung | C12: Punkte | E12: CHF-pro-Aufwandspunkt (Belohnungswert ohne Ziel-Kostenanteil) | F12: CHF mit 50% Vereins-Kostenanteil
A13: Event-Teilnahme | B13: -- | C13: 10 | D13: -- | E13: =C13/D4 -> 0.66666667 | F13: =E13*0.5 -> 0.33333333
A14: Umfragen-Teilnahme | B14: -- | C14: 10 | D14: -- | E14: =C14/D4 -> 0.66666667 | F14: =E14*0.5 -> 0.33333333
A15: Mitglieder-Rekrutierung | B15: -- | C15: 150 | D15: -- | E15: =C15/D4 -> 10 | F15: =E15*0.5 -> 5

Sheet Jahres-Planung
A1: Berechnung der jährlichen Kosten durch das Punktesystem
B3: Anzahl | C3: CHF-pro-Spende | D3: Punkte-pro-CHF | E3: Max. Punkte pro Jahr | F3: Vereins-Einnahmen durch alle Spenden (CHF)
A4: Spenden pro Jahr | B4: 5 | C4: 50 | D4: ='Punkte-Definition'!C7 -> 5 | E4: =B4*D4*C4 -> 1250 | F4: =E4/'Punkte-Definition'!D4 -> 83.333333
B6: Anzahl | C6: Stunden-pro-Aufgabe | D6: Punkte-pro-h | E6: Max. Punkte pro Jahr | F6: Vereins-Ausgaben für alle Aufgaben (Belohnungswert ohne Ziel-Kostenanteil) | G6: Belohnungswert mit 50% Vereins-Kostenanteil
A7: Aufgaben pro Jahr | B7: 30 | C7: 3 | D7: ='Punkte-Definition'!D10 -> 30 | E7: =B7*D7*C7 -> 2700 | F7: =E7/'Punkte-Definition'!D4*-1 -> -180 | G7: =F7*0.5 -> -90
B9: Anzahl | C9: Teilnehmer-pro-Event | D9: Punkte-pro-Event | E9: Max. Punkte pro Jahr | F9: Vereins-Ausgaben für alle Events (Belohnungswert ohne Ziel-Kostenanteil) | G9: Belohnungswert mit 50% Vereins-Kostenanteil
A10: Events pro Jahr | B10: 8 | C10: 15 | D10: ='Punkte-Definition'!C13 -> 10 | E10: =B10*D10*C10 -> 1200 | F10: =E10/'Punkte-Definition'!D4*-1 -> -80 | G10: =F10*0.5 -> -40
A12: Weitere Aktivitäten pro Jahr | B12: Anzahl | C12: Teilnehmer-pro-Aktivität | D12: Punkte-pro-Aktivität | E12: Max. Punkte pro Jahr | F12: Vereins-Ausgaben für alle Aktivitäten (Belohnungswert ohne Ziel-Kostenanteil) | G12: Belohnungswert mit 50% Vereins-Kostenanteil
A13: Umfragen | B13: 2 | C13: 15 | D13: ='Punkte-Definition'!C14 -> 10 | E13: =B13*D13*C13 -> 300 | F13: =E13/'Punkte-Definition'!D4*-1 -> -20 | G13: =F13*0.5 -> -10
A14: Mitglieder-Rekrutierung | B14: 1 | C14: 2 | D14: ='Punkte-Definition'!C15 -> 150 | E14: =B14*D14*C14 -> 300 | F14: =E14/'Punkte-Definition'!D4*-1 -> -20 | G14: =F14*0.5 -> -10
F16: Umsatz durch Punktesystem pro Jahr (Belohnungswert ohne Ziel-Kostenanteil) | G16: Umsatz durch Punktesystem pro Jahr (Belohnungswert mit 50% Vereins-Kostenanteil)
A17: Gesamter Vereins-Umsatz | F17: =SUM(F6:F14,F4) -> -216.66667 | G17: =SUM(G6:G14,F4) -> -66.666667

Sheet Belohnungen
A1: Berechnung der Punkte-Werte für Belohnungen im Verein
B3: Realwert (CHF) | C3: Ziel-Kostenanteil | D3: Zielkosten (CHF) | E3: Punktewert | F3: Aufwand (h)
A4: Beschreibung | B4: Wie viel kostet diese Belohnung? | C4: Wie viel Prozent einer Belohnung übernimmt der Verein? | D4: Wie viel der Kosten für eine Belohung übernimmt der Verein? | E4: Wie viele Punkte sollte diese Belohnung mind. kosten? | F4: Wie viele Arbeits-Stunden ist diese Belohnung wert?
A5: Formel | B5: -- | C5: -- | D5: Zielkosten = Realwert * Ziel-Kostenanteil | E5: Punktewert = Realwert * (Punkte-pro-CHF / Ziel-Kostenanteil) | F5: Stunden = Punktewert / Punkte-pro-h
A7: Belohnung | B7: Realwert (CHF) | C7: Ziel-Kostenanteil (%) | D7: Ziel-Kostenanteil (CHF) | E7: Punktewert | F7: Aufwand (h)
A8: Rabattcode Vereins-Shop | B8: 5 | C8: 50 | D8: =B8*C8*0.01 -> 2.5 | E8: =B8*('Punkte-Definition'!D4/(C8*0.01)) -> 150 | F8: =E8/'Punkte-Definition'!D10 -> 5
A9: Vereins-Merch | B9: 20 | C9: 50 | D9: =B9*C9*0.01 -> 10 | E9: =B9*('Punkte-Definition'!D4/(C9*0.01)) -> 600 | F9: =E9/'Punkte-Definition'!D10 -> 20
A10: Vereins-Mitgliedschaft | B10: 50 | C10: 50 | D10: =B10*C10*0.01 -> 25 | E10: =B10*('Punkte-Definition'!D4/(C10*0.01)) -> 1500 | F10: =E10/'Punkte-Definition'!D10 -> 50

Sheet Punktebeispiel
A1: Punktebeispiel pro Jahr (aktives Mitglied)
A3: Quelle | B3: Anzahl | C3: Punkte
A4: Spenden (CHF) | B4: 30 | C4: =B4*'Punkte-Definition'!D7 -> 150
A5: Aufgabe (h) | B5: 3 | C5: =B5*'Punkte-Definition'!D10 -> 90
A6: Event-Teilnahme | B6: 4 | C6: =B6*'Punkte-Definition'!C13 -> 40
A7: Umfrage | B7: 1 | C7: =B7*'Punkte-Definition'!C14 -> 10
A8: Mitglieder-Rekrutiertung | B8: 1 | C8: =B8*'Punkte-Definition'!C15 -> 150
A10: Gesamt-Punktzahl | C10: =SUM(C4:C8) -> 440
